tigopesa/__init__.py
tigopesa/exceptions.py
tigopesa/utils.py
tigopesa-0.6.dist-info/LICENSE
tigopesa-0.6.dist-info/METADATA
tigopesa-0.6.dist-info/WHEEL
tigopesa-0.6.dist-info/top_level.txt
tigopesa-0.6.dist-info/RECORD
