Metadata-Version: 2.1
Name: tigopesa
Version: 0.6
Summary: A python wrapper for Tigopesa Payment API
Home-page: https://github.com/Kalebu/tigopesa
Author: Jordan Kalebu
Author-email: isaackeinstein@gmail.com
License: MIT
Download-URL: https://github.com/Kalebu/tigopesa/archive/0.2.tar.gz
Keywords: tigopesa payments,mobile paymentspython-tigopesa packagetigopesa-pythontanzania,python-tanzania
Platform: UNKNOWN
Classifier: Development Status :: 3 - Alpha
Classifier: Intended Audience :: Developers
Classifier: Topic :: Software Development :: Build Tools
Classifier: License :: OSI Approved :: MIT License
Classifier: Programming Language :: Python :: 3.6
Classifier: Programming Language :: Python :: 3.7
Classifier: Programming Language :: Python :: 3.8
Classifier: Programming Language :: Python :: 3.9
Requires-Python: >=3.6
Requires-Dist: pydantic
Requires-Dist: requests
